polars_timeseries_utils/__init__.py
polars_timeseries_utils/py.typed
polars_timeseries_utils/preprocessing/__init__.py
polars_timeseries_utils/preprocessing/cleanup.py
polars_timeseries_utils/preprocessing/frequency.py
polars_timeseries_utils/preprocessing/timestamp.py
polars_timeseries_utils/preprocessing/types.py
polars_timeseries_utils/stats/__init__.py
polars_timeseries_utils/stats/zscore.py
polars_timeseries_utils/transformers/__init__.py
polars_timeseries_utils/transformers/composable/__init__.py
polars_timeseries_utils/transformers/composable/base.py
polars_timeseries_utils/transformers/composable/multi_column_transformer.py
polars_timeseries_utils/transformers/composable/pipeline.py
polars_timeseries_utils/transformers/single/__init__.py
polars_timeseries_utils/transformers/single/base.py
polars_timeseries_utils/transformers/single/difference.py
polars_timeseries_utils/transformers/single/impute.py
polars_timeseries_utils/transformers/single/lag.py
polars_timeseries_utils/transformers/single/scale.py
polars_timeseries_utils/transformers/single/smooth.py
polars_timeseries_utils/transformers/single/types.py
polars_timeseries_utils-0.1.6.dist-info/METADATA
polars_timeseries_utils-0.1.6.dist-info/WHEEL
polars_timeseries_utils-0.1.6.dist-info/licenses/LICENSE.txt
polars_timeseries_utils-0.1.6.dist-info/RECORD
